dashserve/__init__.py
dashserve/__main__.py
dashserve/jupyter.py
dashserve/serializer.py
dashserve/server.py
dashserve/wsgi.py
dashserve/tests/__init__.py
dashserve/tests/myapp.py
dashserve/tests/test_dashserve.py
dashserve-0.2.1.dist-info/LICENSE
dashserve-0.2.1.dist-info/METADATA
dashserve-0.2.1.dist-info/WHEEL
dashserve-0.2.1.dist-info/top_level.txt
dashserve-0.2.1.dist-info/RECORD
